cirq_superstaq/__init__.py
cirq_superstaq/_version.py
cirq_superstaq/_version_test.py
cirq_superstaq/compiler_output.py
cirq_superstaq/compiler_output_test.py
cirq_superstaq/daily_integration_test.py
cirq_superstaq/evaluation.py
cirq_superstaq/evaluation_test.py
cirq_superstaq/job.py
cirq_superstaq/job_test.py
cirq_superstaq/py.typed
cirq_superstaq/resource_counters.py
cirq_superstaq/resource_counters_test.py
cirq_superstaq/sampler.py
cirq_superstaq/serialization.py
cirq_superstaq/serialization_test.py
cirq_superstaq/service.py
cirq_superstaq/service_test.py
cirq_superstaq/validation.py
cirq_superstaq/validation_test.py
cirq_superstaq/worker.py
cirq_superstaq/worker_test.py
cirq_superstaq/circuits/__init__.py
cirq_superstaq/circuits/msd.py
cirq_superstaq/circuits/msd_test.py
cirq_superstaq/ops/__init__.py
cirq_superstaq/ops/qubit_gates.py
cirq_superstaq/ops/qubit_gates_test.py
cirq_superstaq/ops/qudit_gates.py
cirq_superstaq/ops/qudit_gates_test.py
cirq_superstaq-0.5.61.dist-info/METADATA
cirq_superstaq-0.5.61.dist-info/WHEEL
cirq_superstaq-0.5.61.dist-info/top_level.txt
cirq_superstaq-0.5.61.dist-info/RECORD
