Metadata-Version: 2.4
Name: cirq-superstaq
Version: 0.5.61
Summary: The Cirq module that provides tools and access to Superstaq.
Author-email: Superstaq development team <superstaq@infleqtion.com>
License: Apache-2.0
Project-URL: homepage, https://github.com/Infleqtion/client-superstaq
Requires-Python: >=3.9.0
Requires-Dist: cirq-core>=1.0.0
Requires-Dist: general-superstaq~=0.5.61
Provides-Extra: dev
Requires-Dist: checks-superstaq~=0.5.61; extra == "dev"
Requires-Dist: qiskit-superstaq~=0.5.61; extra == "dev"
Requires-Dist: stimcirq>=1.15.0; python_version < "3.13" and extra == "dev"
Requires-Dist: stimcirq>=1.15.0; (python_version < "3.14" and (sys_platform == "darwin" or sys_platform == "linux")) and extra == "dev"
Provides-Extra: examples
Requires-Dist: notebook>=6.5.5; extra == "examples"
Requires-Dist: qiskit-superstaq~=0.5.61; extra == "examples"
Provides-Extra: stim
Requires-Dist: stimcirq>=1.15.0; extra == "stim"
